TikSign/Test.py
TikSign/TikSign.py
TikSign/__init__.py
tiksign-0.2.9999999.dist-info/METADATA
tiksign-0.2.9999999.dist-info/WHEEL
tiksign-0.2.9999999.dist-info/top_level.txt
tiksign-0.2.9999999.dist-info/RECORD
